redis_pydict/__init__.py
redis_pydict-0.0.1.dist-info/LICENSE
redis_pydict-0.0.1.dist-info/METADATA
redis_pydict-0.0.1.dist-info/WHEEL
redis_pydict-0.0.1.dist-info/top_level.txt
redis_pydict-0.0.1.dist-info/RECORD
