Metadata-Version: 2.1
Name: redis-pydict
Version: 0.0.1
Summary: A python dictionary that uses Redis as in-memory storage backend to facilitate distributed computing applications development.
Home-page: https://github.com/Narasimha1997/redis-pydict
Author: Narasimha Prasanna HN
Author-email: narasimhaprasannahn@gmail.com
License: MIT
Keywords: python redis distributed-computing dict software-dev
Platform: UNKNOWN
Classifier: Programming Language :: Python :: 3
Classifier: License :: OSI Approved :: MIT License
Classifier: Operating System :: OS Independent
Requires-Dist: redis
